<?xml version="1.0" encoding="utf-8"?>
<clothing-items>
 <clothing>
  <id>
   445938606
  </id>
  <name>
   Under Armour Umbrellas K-7094
  </name>
  <category>
   Umbrellas
  </category>
  <size>
   XXL
  </size>
  <color>
   Голубой
  </color>
  <material>
   Вискоза
  </material>
  <price>
   611421
  </price>
  <rating>
   3.3
  </rating>
  <reviews>
   217577
  </reviews>
  <new>
   +
  </new>
  <exclusive>
   no
  </exclusive>
 </clothing>
 <clothing>
  <id>
   223012394
  </id>
  <name>
   Puma T-shirt X-9104
  </name>
  <category>
   T-shirt
  </category>
  <size>
   M
  </size>
  <color>
   Оранжевый
  </color>
  <material>
   Шелк
  </material>
  <price>
   617115
  </price>
  <rating>
   4.2
  </rating>
  <reviews>
   100293
  </reviews>
  <new>
   -
  </new>
  <exclusive>
   no
  </exclusive>
 </clothing>
 <clothing>
  <id>
   492472693
  </id>
  <name>
   Adidas Shirt Z-4071
  </name>
  <category>
   Shirt
  </category>
  <size>
   M
  </size>
  <color>
   Желтый
  </color>
  <material>
   Хлопок
  </material>
  <price>
   856936
  </price>
  <rating>
   2.04
  </rating>
  <reviews>
   580541
  </reviews>
  <new>
   +
  </new>
 </clothing>
 <clothing>
  <id>
   777223176
  </id>
  <name>
   Converse Blouse U-8031
  </name>
  <category>
   Blouse
  </category>
  <size>
   XXL
  </size>
  <color>
   Синий
  </color>
  <material>
   Нейлон
  </material>
  <price>
   753705
  </price>
  <rating>
   1.36
  </rating>
  <reviews>
   257012
  </reviews>
  <new>
   -
  </new>
  <exclusive>
   yes
  </exclusive>
 </clothing>
 <clothing>
  <id>
   129349500
  </id>
  <name>
   Asics Shoes A-7679
  </name>
  <category>
   Shoes
  </category>
  <size>
   XXL
  </size>
  <color>
   Желтый
  </color>
  <material>
   Шелк
  </material>
  <price>
   630701
  </price>
  <rating>
   2.53
  </rating>
  <reviews>
   982914
  </reviews>
  <new>
   -
  </new>
  <sporty>
   yes
  </sporty>
 </clothing>
 <clothing>
  <id>
   347260948
  </id>
  <name>
   Ellesse Socks G-2161
  </name>
  <category>
   Socks
  </category>
  <size>
   XL
  </size>
  <color>
   Красный
  </color>
  <material>
   Нейлон
  </material>
  <price>
   801114
  </price>
  <rating>
   2.33
  </rating>
  <reviews>
   948413
  </reviews>
  <new>
   -
  </new>
  <exclusive>
   no
  </exclusive>
  <sporty>
   yes
  </sporty>
 </clothing>
 <clothing>
  <id>
   785228561
  </id>
  <name>
   Puma T-shirt I-4471
  </name>
  <category>
   T-shirt
  </category>
  <size>
   XL
  </size>
  <color>
   Желтый
  </color>
  <material>
   Полиэстер
  </material>
  <price>
   647734
  </price>
  <rating>
   2.1
  </rating>
  <reviews>
   455674
  </reviews>
  <new>
   -
  </new>
  <exclusive>
   no
  </exclusive>
  <sporty>
   no
  </sporty>
 </clothing>
 <clothing>
  <id>
   553888209
  </id>
  <name>
   PleinSport Hat D-4621
  </name>
  <category>
   Hat
  </category>
  <size>
   L
  </size>
  <color>
   Желтый
  </color>
  <material>
   Кожа
  </material>
  <price>
   709669
  </price>
  <rating>
   3.98
  </rating>
  <reviews>
   300559
  </reviews>
  <new>
   -
  </new>
  <sporty>
   no
  </sporty>
 </clothing>
 <clothing>
  <id>
   841616525
  </id>
  <name>
   Nike Shirt P-1310
  </name>
  <category>
   Shirt
  </category>
  <size>
   S
  </size>
  <color>
   Фиолетовый
  </color>
  <material>
   Кожа
  </material>
  <price>
   986295
  </price>
  <rating>
   3.04
  </rating>
  <reviews>
   627259
  </reviews>
  <new>
   +
  </new>
 </clothing>
 <clothing>
  <id>
   411223315
  </id>
  <name>
   PleinSport Handbags Z-4543
  </name>
  <category>
   Handbags
  </category>
  <size>
   L
  </size>
  <color>
   Красный
  </color>
  <material>
   Шерсть
  </material>
  <price>
   340677
  </price>
  <rating>
   4.58
  </rating>
  <reviews>
   97894
  </reviews>
  <new>
   +
  </new>
  <exclusive>
   no
  </exclusive>
  <sporty>
   no
  </sporty>
 </clothing>
 <clothing>
  <id>
   328904238
  </id>
  <name>
   Nike Handbags C-6505
  </name>
  <category>
   Handbags
  </category>
  <size>
   XL
  </size>
  <color>
   Фиолетовый
  </color>
  <material>
   Лен
  </material>
  <price>
   611104
  </price>
  <rating>
   4.26
  </rating>
  <reviews>
   23468
  </reviews>
  <exclusive>
   yes
  </exclusive>
  <sporty>
   no
  </sporty>
 </clothing>
 <clothing>
  <id>
   279454074
  </id>
  <name>
   Reebok Dress C-5810
  </name>
  <category>
   Dress
  </category>
  <size>
   L
  </size>
  <color>
   Красный
  </color>
  <material>
   Лен
  </material>
  <price>
   240287
  </price>
  <rating>
   1.04
  </rating>
  <reviews>
   587102
  </reviews>
 </clothing>
 <clothing>
  <id>
   664335247
  </id>
  <name>
   Adidas Hat M-2898
  </name>
  <category>
   Hat
  </category>
  <size>
   S
  </size>
  <color>
   Зеленый
  </color>
  <material>
   Лен
  </material>
  <price>
   991517
  </price>
  <rating>
   3.71
  </rating>
  <reviews>
   159813
  </reviews>
  <new>
   -
  </new>
  <exclusive>
   yes
  </exclusive>
  <sporty>
   yes
  </sporty>
 </clothing>
 <clothing>
  <id>
   865183905
  </id>
  <name>
   Reebok Pants A-7971
  </name>
  <category>
   Pants
  </category>
  <size>
   M
  </size>
  <color>
   Красный
  </color>
  <material>
   Хлопок
  </material>
  <price>
   924812
  </price>
  <rating>
   4.08
  </rating>
  <reviews>
   272716
  </reviews>
 </clothing>
 <clothing>
  <id>
   137751986
  </id>
  <name>
   Puma Pants V-6606
  </name>
  <category>
   Pants
  </category>
  <size>
   XL
  </size>
  <color>
   Фиолетовый
  </color>
  <material>
   Кожа
  </material>
  <price>
   287878
  </price>
  <rating>
   1.07
  </rating>
  <reviews>
   533043
  </reviews>
  <new>
   -
  </new>
  <exclusive>
   no
  </exclusive>
 </clothing>
 <clothing>
  <id>
   492901115
  </id>
  <name>
   Under Armour Sweater H-9159
  </name>
  <category>
   Sweater
  </category>
  <size>
   S
  </size>
  <color>
   Зеленый
  </color>
  <material>
   Нейлон
  </material>
  <price>
   508196
  </price>
  <rating>
   3.8
  </rating>
  <reviews>
   923878
  </reviews>
  <new>
   -
  </new>
  <sporty>
   no
  </sporty>
 </clothing>
 <clothing>
  <id>
   410187636
  </id>
  <name>
   Adidas Dress P-9795
  </name>
  <category>
   Dress
  </category>
  <size>
   XL
  </size>
  <color>
   Фиолетовый
  </color>
  <material>
   Шелк
  </material>
  <price>
   635080
  </price>
  <rating>
   4.24
  </rating>
  <reviews>
   397583
  </reviews>
  <exclusive>
   yes
  </exclusive>
  <sporty>
   no
  </sporty>
 </clothing>
 <clothing>
  <id>
   537191224
  </id>
  <name>
   Vans Jeans Z-4649
  </name>
  <category>
   Jeans
  </category>
  <size>
   XL
  </size>
  <color>
   Желтый
  </color>
  <material>
   Нейлон
  </material>
  <price>
   317456
  </price>
  <rating>
   3.68
  </rating>
  <reviews>
   609137
  </reviews>
  <exclusive>
   no
  </exclusive>
  <sporty>
   no
  </sporty>
 </clothing>
 <clothing>
  <id>
   451936530
  </id>
  <name>
   Under Armour Blouse Q-7062
  </name>
  <category>
   Blouse
  </category>
  <size>
   S
  </size>
  <color>
   Оранжевый
  </color>
  <material>
   Хлопок
  </material>
  <price>
   482818
  </price>
  <rating>
   5.0
  </rating>
  <reviews>
   307170
  </reviews>
  <exclusive>
   yes
  </exclusive>
 </clothing>
 <clothing>
  <id>
   740477397
  </id>
  <name>
   PleinSport Gloves K-2846
  </name>
  <category>
   Gloves
  </category>
  <size>
   XXL
  </size>
  <color>
   Синий
  </color>
  <material>
   Кожа
  </material>
  <price>
   505778
  </price>
  <rating>
   3.15
  </rating>
  <reviews>
   245377
  </reviews>
  <exclusive>
   yes
  </exclusive>
  <sporty>
   no
  </sporty>
 </clothing>
 <clothing>
  <id>
   903202609
  </id>
  <name>
   Ellesse Pants N-5085
  </name>
  <category>
   Pants
  </category>
  <size>
   L
  </size>
  <color>
   Желтый
  </color>
  <material>
   Полиэстер
  </material>
  <price>
   924758
  </price>
  <rating>
   1.42
  </rating>
  <reviews>
   877260
  </reviews>
  <new>
   +
  </new>
  <exclusive>
   no
  </exclusive>
 </clothing>
 <clothing>
  <id>
   976432543
  </id>
  <name>
   PleinSport Dress T-6680
  </name>
  <category>
   Dress
  </category>
  <size>
   XL
  </size>
  <color>
   Фиолетовый
  </color>
  <material>
   Хлопок
  </material>
  <price>
   732479
  </price>
  <rating>
   1.54
  </rating>
  <reviews>
   28318
  </reviews>
  <new>
   -
  </new>
  <exclusive>
   yes
  </exclusive>
  <sporty>
   no
  </sporty>
 </clothing>
 <clothing>
  <id>
   694793587
  </id>
  <name>
   Reebok Umbrellas A-7156
  </name>
  <category>
   Umbrellas
  </category>
  <size>
   L
  </size>
  <color>
   Фиолетовый
  </color>
  <material>
   Хлопок
  </material>
  <price>
   409767
  </price>
  <rating>
   3.38
  </rating>
  <reviews>
   690634
  </reviews>
  <exclusive>
   yes
  </exclusive>
 </clothing>
 <clothing>
  <id>
   192372041
  </id>
  <name>
   Asics Pants A-4203
  </name>
  <category>
   Pants
  </category>
  <size>
   XXL
  </size>
  <color>
   Оранжевый
  </color>
  <material>
   Шелк
  </material>
  <price>
   102753
  </price>
  <rating>
   3.85
  </rating>
  <reviews>
   474535
  </reviews>
  <exclusive>
   no
  </exclusive>
  <sporty>
   no
  </sporty>
 </clothing>
 <clothing>
  <id>
   224713499
  </id>
  <name>
   DC Shirt U-4061
  </name>
  <category>
   Shirt
  </category>
  <size>
   XL
  </size>
  <color>
   Синий
  </color>
  <material>
   Кожа
  </material>
  <price>
   586005
  </price>
  <rating>
   1.05
  </rating>
  <reviews>
   573449
  </reviews>
  <new>
   -
  </new>
 </clothing>
 <clothing>
  <id>
   895836024
  </id>
  <name>
   PleinSport Dress V-8088
  </name>
  <category>
   Dress
  </category>
  <size>
   S
  </size>
  <color>
   Красный
  </color>
  <material>
   Кожа
  </material>
  <price>
   836559
  </price>
  <rating>
   4.64
  </rating>
  <reviews>
   134040
  </reviews>
 </clothing>
 <clothing>
  <id>
   584555058
  </id>
  <name>
   Asics Shoes X-3072
  </name>
  <category>
   Shoes
  </category>
  <size>
   XL
  </size>
  <color>
   Оранжевый
  </color>
  <material>
   Вискоза
  </material>
  <price>
   857473
  </price>
  <rating>
   3.23
  </rating>
  <reviews>
   608620
  </reviews>
  <new>
   +
  </new>
  <exclusive>
   yes
  </exclusive>
  <sporty>
   yes
  </sporty>
 </clothing>
 <clothing>
  <id>
   324700032
  </id>
  <name>
   PleinSport Shirt C-4117
  </name>
  <category>
   Shirt
  </category>
  <size>
   XXL
  </size>
  <color>
   Красный
  </color>
  <material>
   Шелк
  </material>
  <price>
   857671
  </price>
  <rating>
   3.08
  </rating>
  <reviews>
   848272
  </reviews>
  <new>
   +
  </new>
 </clothing>
 <clothing>
  <id>
   113078567
  </id>
  <name>
   Converse Shoes I-6029
  </name>
  <category>
   Shoes
  </category>
  <size>
   M
  </size>
  <color>
   Оранжевый
  </color>
  <material>
   Лен
  </material>
  <price>
   598253
  </price>
  <rating>
   4.44
  </rating>
  <reviews>
   455418
  </reviews>
  <exclusive>
   no
  </exclusive>
 </clothing>
 <clothing>
  <id>
   939973216
  </id>
  <name>
   New Balance Sweater H-3928
  </name>
  <category>
   Sweater
  </category>
  <size>
   L
  </size>
  <color>
   Желтый
  </color>
  <material>
   Кожа
  </material>
  <price>
   676371
  </price>
  <rating>
   2.76
  </rating>
  <reviews>
   392146
  </reviews>
  <exclusive>
   no
  </exclusive>
  <sporty>
   yes
  </sporty>
 </clothing>
 <clothing>
  <id>
   140086596
  </id>
  <name>
   Reebok Jacket B-6461
  </name>
  <category>
   Jacket
  </category>
  <size>
   M
  </size>
  <color>
   Зеленый
  </color>
  <material>
   Лен
  </material>
  <price>
   717959
  </price>
  <rating>
   3.36
  </rating>
  <reviews>
   804424
  </reviews>
  <new>
   -
  </new>
  <exclusive>
   no
  </exclusive>
  <sporty>
   no
  </sporty>
 </clothing>
</clothing-items>
