<?xml version="1.0" encoding="utf-8"?>
<clothing-items>
 <clothing>
  <id>
   290444828
  </id>
  <name>
   Under Armour Hat T-2123
  </name>
  <category>
   Hat
  </category>
  <size>
   XL
  </size>
  <color>
   Голубой
  </color>
  <material>
   Нейлон
  </material>
  <price>
   941740
  </price>
  <rating>
   1.55
  </rating>
  <reviews>
   284148
  </reviews>
  <exclusive>
   no
  </exclusive>
  <sporty>
   no
  </sporty>
 </clothing>
 <clothing>
  <id>
   871617028
  </id>
  <name>
   Fila T-shirt U-9876
  </name>
  <category>
   T-shirt
  </category>
  <size>
   M
  </size>
  <color>
   Оранжевый
  </color>
  <material>
   Шелк
  </material>
  <price>
   841707
  </price>
  <rating>
   1.8
  </rating>
  <reviews>
   814185
  </reviews>
  <new>
   +
  </new>
  <sporty>
   no
  </sporty>
 </clothing>
 <clothing>
  <id>
   696164966
  </id>
  <name>
   Brooks Socks A-7885
  </name>
  <category>
   Socks
  </category>
  <size>
   S
  </size>
  <color>
   Голубой
  </color>
  <material>
   Нейлон
  </material>
  <price>
   581595
  </price>
  <rating>
   1.44
  </rating>
  <reviews>
   789381
  </reviews>
  <new>
   -
  </new>
  <sporty>
   yes
  </sporty>
 </clothing>
 <clothing>
  <id>
   453241758
  </id>
  <name>
   Ellesse Shirt X-5688
  </name>
  <category>
   Shirt
  </category>
  <size>
   XL
  </size>
  <color>
   Голубой
  </color>
  <material>
   Хлопок
  </material>
  <price>
   792210
  </price>
  <rating>
   1.91
  </rating>
  <reviews>
   460956
  </reviews>
  <new>
   -
  </new>
 </clothing>
 <clothing>
  <id>
   944121763
  </id>
  <name>
   New Balance Blouse S-5907
  </name>
  <category>
   Blouse
  </category>
  <size>
   XXL
  </size>
  <color>
   Оранжевый
  </color>
  <material>
   Лен
  </material>
  <price>
   317472
  </price>
  <rating>
   3.82
  </rating>
  <reviews>
   568360
  </reviews>
  <new>
   -
  </new>
  <exclusive>
   no
  </exclusive>
  <sporty>
   yes
  </sporty>
 </clothing>
 <clothing>
  <id>
   254132183
  </id>
  <name>
   Puma Hat Z-7926
  </name>
  <category>
   Hat
  </category>
  <size>
   L
  </size>
  <color>
   Фиолетовый
  </color>
  <material>
   Полиэстер
  </material>
  <price>
   262885
  </price>
  <rating>
   3.47
  </rating>
  <reviews>
   571114
  </reviews>
  <exclusive>
   no
  </exclusive>
 </clothing>
 <clothing>
  <id>
   591199250
  </id>
  <name>
   DC Gloves J-9842
  </name>
  <category>
   Gloves
  </category>
  <size>
   M
  </size>
  <color>
   Желтый
  </color>
  <material>
   Лен
  </material>
  <price>
   507412
  </price>
  <rating>
   4.74
  </rating>
  <reviews>
   918530
  </reviews>
  <new>
   -
  </new>
  <sporty>
   no
  </sporty>
 </clothing>
 <clothing>
  <id>
   164884867
  </id>
  <name>
   PleinSport Shoes B-8579
  </name>
  <category>
   Shoes
  </category>
  <size>
   M
  </size>
  <color>
   Фиолетовый
  </color>
  <material>
   Лен
  </material>
  <price>
   168234
  </price>
  <rating>
   2.03
  </rating>
  <reviews>
   149488
  </reviews>
  <exclusive>
   no
  </exclusive>
 </clothing>
 <clothing>
  <id>
   219704197
  </id>
  <name>
   Converse Umbrellas K-4956
  </name>
  <category>
   Umbrellas
  </category>
  <size>
   M
  </size>
  <color>
   Зеленый
  </color>
  <material>
   Вискоза
  </material>
  <price>
   205693
  </price>
  <rating>
   3.3
  </rating>
  <reviews>
   402198
  </reviews>
  <sporty>
   no
  </sporty>
 </clothing>
 <clothing>
  <id>
   977017031
  </id>
  <name>
   PleinSport T-shirt G-7160
  </name>
  <category>
   T-shirt
  </category>
  <size>
   M
  </size>
  <color>
   Желтый
  </color>
  <material>
   Шерсть
  </material>
  <price>
   105725
  </price>
  <rating>
   1.76
  </rating>
  <reviews>
   966635
  </reviews>
  <new>
   +
  </new>
  <exclusive>
   yes
  </exclusive>
  <sporty>
   no
  </sporty>
 </clothing>
 <clothing>
  <id>
   648587094
  </id>
  <name>
   Brooks Handbags P-1701
  </name>
  <category>
   Handbags
  </category>
  <size>
   M
  </size>
  <color>
   Голубой
  </color>
  <material>
   Лен
  </material>
  <price>
   256425
  </price>
  <rating>
   2.73
  </rating>
  <reviews>
   950621
  </reviews>
  <new>
   -
  </new>
 </clothing>
 <clothing>
  <id>
   736215641
  </id>
  <name>
   PleinSport Gloves G-9393
  </name>
  <category>
   Gloves
  </category>
  <size>
   L
  </size>
  <color>
   Голубой
  </color>
  <material>
   Хлопок
  </material>
  <price>
   436939
  </price>
  <rating>
   2.61
  </rating>
  <reviews>
   603456
  </reviews>
  <new>
   -
  </new>
  <exclusive>
   yes
  </exclusive>
 </clothing>
 <clothing>
  <id>
   976635083
  </id>
  <name>
   New Balance Pants J-8931
  </name>
  <category>
   Pants
  </category>
  <size>
   L
  </size>
  <color>
   Голубой
  </color>
  <material>
   Шелк
  </material>
  <price>
   455220
  </price>
  <rating>
   4.8
  </rating>
  <reviews>
   740960
  </reviews>
  <new>
   -
  </new>
  <exclusive>
   no
  </exclusive>
 </clothing>
 <clothing>
  <id>
   719913986
  </id>
  <name>
   Converse Socks G-1253
  </name>
  <category>
   Socks
  </category>
  <size>
   XL
  </size>
  <color>
   Оранжевый
  </color>
  <material>
   Полиэстер
  </material>
  <price>
   923112
  </price>
  <rating>
   3.27
  </rating>
  <reviews>
   74253
  </reviews>
  <new>
   +
  </new>
  <exclusive>
   yes
  </exclusive>
 </clothing>
 <clothing>
  <id>
   893059328
  </id>
  <name>
   New Balance Shirt W-6312
  </name>
  <category>
   Shirt
  </category>
  <size>
   M
  </size>
  <color>
   Зеленый
  </color>
  <material>
   Хлопок
  </material>
  <price>
   885668
  </price>
  <rating>
   4.5
  </rating>
  <reviews>
   130905
  </reviews>
  <exclusive>
   no
  </exclusive>
  <sporty>
   no
  </sporty>
 </clothing>
 <clothing>
  <id>
   298994801
  </id>
  <name>
   Under Armour Shirt F-3514
  </name>
  <category>
   Shirt
  </category>
  <size>
   S
  </size>
  <color>
   Синий
  </color>
  <material>
   Полиэстер
  </material>
  <price>
   969534
  </price>
  <rating>
   4.53
  </rating>
  <reviews>
   79049
  </reviews>
  <new>
   -
  </new>
  <exclusive>
   no
  </exclusive>
 </clothing>
 <clothing>
  <id>
   482898731
  </id>
  <name>
   Ellesse Dress O-9730
  </name>
  <category>
   Dress
  </category>
  <size>
   S
  </size>
  <color>
   Фиолетовый
  </color>
  <material>
   Кожа
  </material>
  <price>
   627477
  </price>
  <rating>
   4.48
  </rating>
  <reviews>
   840541
  </reviews>
  <new>
   -
  </new>
  <exclusive>
   yes
  </exclusive>
 </clothing>
 <clothing>
  <id>
   693651323
  </id>
  <name>
   Asics Handbags G-7755
  </name>
  <category>
   Handbags
  </category>
  <size>
   S
  </size>
  <color>
   Голубой
  </color>
  <material>
   Полиэстер
  </material>
  <price>
   850301
  </price>
  <rating>
   3.71
  </rating>
  <reviews>
   206061
  </reviews>
  <sporty>
   no
  </sporty>
 </clothing>
 <clothing>
  <id>
   816110774
  </id>
  <name>
   Addidas Blouse C-2635
  </name>
  <category>
   Blouse
  </category>
  <size>
   S
  </size>
  <color>
   Синий
  </color>
  <material>
   Полиэстер
  </material>
  <price>
   530087
  </price>
  <rating>
   3.06
  </rating>
  <reviews>
   208575
  </reviews>
 </clothing>
 <clothing>
  <id>
   190919130
  </id>
  <name>
   Lacoste T-shirt D-9978
  </name>
  <category>
   T-shirt
  </category>
  <size>
   L
  </size>
  <color>
   Фиолетовый
  </color>
  <material>
   Лен
  </material>
  <price>
   632093
  </price>
  <rating>
   3.42
  </rating>
  <reviews>
   653876
  </reviews>
  <exclusive>
   no
  </exclusive>
 </clothing>
 <clothing>
  <id>
   851498363
  </id>
  <name>
   Addidas Skirt I-1818
  </name>
  <category>
   Skirt
  </category>
  <size>
   M
  </size>
  <color>
   Зеленый
  </color>
  <material>
   Полиэстер
  </material>
  <price>
   807162
  </price>
  <rating>
   3.1
  </rating>
  <reviews>
   665897
  </reviews>
  <exclusive>
   no
  </exclusive>
 </clothing>
 <clothing>
  <id>
   879991657
  </id>
  <name>
   Addidas Umbrellas R-4505
  </name>
  <category>
   Umbrellas
  </category>
  <size>
   S
  </size>
  <color>
   Голубой
  </color>
  <material>
   Хлопок
  </material>
  <price>
   143753
  </price>
  <rating>
   4.06
  </rating>
  <reviews>
   604808
  </reviews>
  <sporty>
   yes
  </sporty>
 </clothing>
 <clothing>
  <id>
   578428653
  </id>
  <name>
   Asics Belts X-3744
  </name>
  <category>
   Belts
  </category>
  <size>
   XXL
  </size>
  <color>
   Синий
  </color>
  <material>
   Хлопок
  </material>
  <price>
   329102
  </price>
  <rating>
   1.09
  </rating>
  <reviews>
   674168
  </reviews>
  <exclusive>
   no
  </exclusive>
  <sporty>
   no
  </sporty>
 </clothing>
 <clothing>
  <id>
   286251962
  </id>
  <name>
   Reebok Socks K-3518
  </name>
  <category>
   Socks
  </category>
  <size>
   XL
  </size>
  <color>
   Фиолетовый
  </color>
  <material>
   Шелк
  </material>
  <price>
   949900
  </price>
  <rating>
   3.43
  </rating>
  <reviews>
   446311
  </reviews>
  <new>
   -
  </new>
  <exclusive>
   no
  </exclusive>
  <sporty>
   no
  </sporty>
 </clothing>
 <clothing>
  <id>
   163948445
  </id>
  <name>
   DC Gloves F-3183
  </name>
  <category>
   Gloves
  </category>
  <size>
   M
  </size>
  <color>
   Зеленый
  </color>
  <material>
   Шерсть
  </material>
  <price>
   525532
  </price>
  <rating>
   1.3
  </rating>
  <reviews>
   325213
  </reviews>
  <exclusive>
   no
  </exclusive>
 </clothing>
 <clothing>
  <id>
   285582569
  </id>
  <name>
   Brooks Handbags J-1356
  </name>
  <category>
   Handbags
  </category>
  <size>
   S
  </size>
  <color>
   Фиолетовый
  </color>
  <material>
   Кожа
  </material>
  <price>
   297421
  </price>
  <rating>
   1.31
  </rating>
  <reviews>
   771415
  </reviews>
  <exclusive>
   no
  </exclusive>
 </clothing>
</clothing-items>
