<?xml version="1.0" encoding="utf-8"?>
<clothing-items>
 <clothing>
  <id>
   146891898
  </id>
  <name>
   Lacoste Gloves L-1697
  </name>
  <category>
   Gloves
  </category>
  <size>
   L
  </size>
  <color>
   Зеленый
  </color>
  <material>
   Хлопок
  </material>
  <price>
   595506
  </price>
  <rating>
   2.87
  </rating>
  <reviews>
   935305
  </reviews>
  <sporty>
   yes
  </sporty>
 </clothing>
 <clothing>
  <id>
   519112243
  </id>
  <name>
   Puma Jeans Q-8607
  </name>
  <category>
   Jeans
  </category>
  <size>
   S
  </size>
  <color>
   Фиолетовый
  </color>
  <material>
   Лен
  </material>
  <price>
   961933
  </price>
  <rating>
   1.49
  </rating>
  <reviews>
   803278
  </reviews>
  <new>
   +
  </new>
  <exclusive>
   yes
  </exclusive>
  <sporty>
   no
  </sporty>
 </clothing>
 <clothing>
  <id>
   827039265
  </id>
  <name>
   Lacoste Gloves B-3446
  </name>
  <category>
   Gloves
  </category>
  <size>
   XXL
  </size>
  <color>
   Оранжевый
  </color>
  <material>
   Шелк
  </material>
  <price>
   817831
  </price>
  <rating>
   3.58
  </rating>
  <reviews>
   278984
  </reviews>
  <exclusive>
   no
  </exclusive>
 </clothing>
 <clothing>
  <id>
   732056092
  </id>
  <name>
   Addidas Jeans V-8349
  </name>
  <category>
   Jeans
  </category>
  <size>
   XL
  </size>
  <color>
   Голубой
  </color>
  <material>
   Хлопок
  </material>
  <price>
   948809
  </price>
  <rating>
   4.04
  </rating>
  <reviews>
   292900
  </reviews>
  <new>
   +
  </new>
 </clothing>
 <clothing>
  <id>
   581224389
  </id>
  <name>
   Reebok Shirt S-6945
  </name>
  <category>
   Shirt
  </category>
  <size>
   L
  </size>
  <color>
   Синий
  </color>
  <material>
   Хлопок
  </material>
  <price>
   682183
  </price>
  <rating>
   4.8
  </rating>
  <reviews>
   517096
  </reviews>
  <new>
   -
  </new>
  <sporty>
   yes
  </sporty>
 </clothing>
 <clothing>
  <id>
   944536363
  </id>
  <name>
   Puma Socks C-5993
  </name>
  <category>
   Socks
  </category>
  <size>
   XXL
  </size>
  <color>
   Оранжевый
  </color>
  <material>
   Полиэстер
  </material>
  <price>
   665405
  </price>
  <rating>
   2.76
  </rating>
  <reviews>
   280690
  </reviews>
  <new>
   -
  </new>
  <sporty>
   no
  </sporty>
 </clothing>
 <clothing>
  <id>
   652728167
  </id>
  <name>
   Asics Jeans D-5152
  </name>
  <category>
   Jeans
  </category>
  <size>
   S
  </size>
  <color>
   Красный
  </color>
  <material>
   Нейлон
  </material>
  <price>
   952470
  </price>
  <rating>
   1.12
  </rating>
  <reviews>
   250327
  </reviews>
  <sporty>
   yes
  </sporty>
 </clothing>
 <clothing>
  <id>
   419894367
  </id>
  <name>
   Asics Umbrellas O-8005
  </name>
  <category>
   Umbrellas
  </category>
  <size>
   XL
  </size>
  <color>
   Синий
  </color>
  <material>
   Хлопок
  </material>
  <price>
   115226
  </price>
  <rating>
   4.14
  </rating>
  <reviews>
   788145
  </reviews>
  <exclusive>
   yes
  </exclusive>
  <sporty>
   no
  </sporty>
 </clothing>
 <clothing>
  <id>
   113436655
  </id>
  <name>
   Brooks T-shirt D-5142
  </name>
  <category>
   T-shirt
  </category>
  <size>
   L
  </size>
  <color>
   Оранжевый
  </color>
  <material>
   Шерсть
  </material>
  <price>
   114168
  </price>
  <rating>
   3.59
  </rating>
  <reviews>
   897388
  </reviews>
  <exclusive>
   yes
  </exclusive>
  <sporty>
   yes
  </sporty>
 </clothing>
 <clothing>
  <id>
   880761764
  </id>
  <name>
   Ellesse Pants K-1526
  </name>
  <category>
   Pants
  </category>
  <size>
   XL
  </size>
  <color>
   Зеленый
  </color>
  <material>
   Кожа
  </material>
  <price>
   118700
  </price>
  <rating>
   4.15
  </rating>
  <reviews>
   967646
  </reviews>
  <new>
   +
  </new>
  <exclusive>
   yes
  </exclusive>
  <sporty>
   yes
  </sporty>
 </clothing>
 <clothing>
  <id>
   553109070
  </id>
  <name>
   Fila Hat Y-9276
  </name>
  <category>
   Hat
  </category>
  <size>
   S
  </size>
  <color>
   Оранжевый
  </color>
  <material>
   Шелк
  </material>
  <price>
   567190
  </price>
  <rating>
   3.99
  </rating>
  <reviews>
   908808
  </reviews>
  <sporty>
   no
  </sporty>
 </clothing>
 <clothing>
  <id>
   881541883
  </id>
  <name>
   Brooks Pants P-2939
  </name>
  <category>
   Pants
  </category>
  <size>
   L
  </size>
  <color>
   Красный
  </color>
  <material>
   Вискоза
  </material>
  <price>
   500466
  </price>
  <rating>
   4.09
  </rating>
  <reviews>
   446320
  </reviews>
  <new>
   +
  </new>
  <exclusive>
   yes
  </exclusive>
 </clothing>
 <clothing>
  <id>
   635771847
  </id>
  <name>
   Fila Dress F-2104
  </name>
  <category>
   Dress
  </category>
  <size>
   XL
  </size>
  <color>
   Красный
  </color>
  <material>
   Полиэстер
  </material>
  <price>
   590569
  </price>
  <rating>
   3.55
  </rating>
  <reviews>
   801498
  </reviews>
  <sporty>
   yes
  </sporty>
 </clothing>
 <clothing>
  <id>
   721736277
  </id>
  <name>
   Vans Socks Y-9411
  </name>
  <category>
   Socks
  </category>
  <size>
   S
  </size>
  <color>
   Голубой
  </color>
  <material>
   Вискоза
  </material>
  <price>
   418162
  </price>
  <rating>
   2.87
  </rating>
  <reviews>
   572262
  </reviews>
  <new>
   +
  </new>
 </clothing>
 <clothing>
  <id>
   281576642
  </id>
  <name>
   Reebok Pants X-3685
  </name>
  <category>
   Pants
  </category>
  <size>
   XXL
  </size>
  <color>
   Зеленый
  </color>
  <material>
   Лен
  </material>
  <price>
   451090
  </price>
  <rating>
   4.21
  </rating>
  <reviews>
   206645
  </reviews>
  <exclusive>
   no
  </exclusive>
  <sporty>
   no
  </sporty>
 </clothing>
 <clothing>
  <id>
   328272281
  </id>
  <name>
   Asics Jacket X-8046
  </name>
  <category>
   Jacket
  </category>
  <size>
   L
  </size>
  <color>
   Зеленый
  </color>
  <material>
   Полиэстер
  </material>
  <price>
   668171
  </price>
  <rating>
   2.69
  </rating>
  <reviews>
   124373
  </reviews>
  <exclusive>
   no
  </exclusive>
  <sporty>
   no
  </sporty>
 </clothing>
 <clothing>
  <id>
   923034738
  </id>
  <name>
   Reebok Shoes V-4884
  </name>
  <category>
   Shoes
  </category>
  <size>
   XXL
  </size>
  <color>
   Фиолетовый
  </color>
  <material>
   Нейлон
  </material>
  <price>
   713137
  </price>
  <rating>
   3.55
  </rating>
  <reviews>
   256270
  </reviews>
  <new>
   -
  </new>
  <sporty>
   yes
  </sporty>
 </clothing>
 <clothing>
  <id>
   967450866
  </id>
  <name>
   Adidas Skirt T-5318
  </name>
  <category>
   Skirt
  </category>
  <size>
   M
  </size>
  <color>
   Голубой
  </color>
  <material>
   Нейлон
  </material>
  <price>
   993315
  </price>
  <rating>
   3.14
  </rating>
  <reviews>
   456939
  </reviews>
  <sporty>
   no
  </sporty>
 </clothing>
 <clothing>
  <id>
   660485621
  </id>
  <name>
   Nike Skirt L-4633
  </name>
  <category>
   Skirt
  </category>
  <size>
   XL
  </size>
  <color>
   Оранжевый
  </color>
  <material>
   Лен
  </material>
  <price>
   417600
  </price>
  <rating>
   2.65
  </rating>
  <reviews>
   662265
  </reviews>
  <new>
   -
  </new>
  <exclusive>
   no
  </exclusive>
  <sporty>
   yes
  </sporty>
 </clothing>
 <clothing>
  <id>
   636720367
  </id>
  <name>
   Nike Dress H-9148
  </name>
  <category>
   Dress
  </category>
  <size>
   M
  </size>
  <color>
   Зеленый
  </color>
  <material>
   Кожа
  </material>
  <price>
   145368
  </price>
  <rating>
   2.2
  </rating>
  <reviews>
   872030
  </reviews>
  <sporty>
   no
  </sporty>
 </clothing>
 <clothing>
  <id>
   303049213
  </id>
  <name>
   DC Sweater C-7966
  </name>
  <category>
   Sweater
  </category>
  <size>
   M
  </size>
  <color>
   Зеленый
  </color>
  <material>
   Лен
  </material>
  <price>
   495664
  </price>
  <rating>
   2.37
  </rating>
  <reviews>
   546322
  </reviews>
 </clothing>
 <clothing>
  <id>
   631012776
  </id>
  <name>
   Asics Hat U-1377
  </name>
  <category>
   Hat
  </category>
  <size>
   M
  </size>
  <color>
   Красный
  </color>
  <material>
   Лен
  </material>
  <price>
   187743
  </price>
  <rating>
   2.06
  </rating>
  <reviews>
   474013
  </reviews>
  <exclusive>
   no
  </exclusive>
 </clothing>
 <clothing>
  <id>
   874515892
  </id>
  <name>
   Vans Handbags T-4486
  </name>
  <category>
   Handbags
  </category>
  <size>
   XL
  </size>
  <color>
   Голубой
  </color>
  <material>
   Нейлон
  </material>
  <price>
   550861
  </price>
  <rating>
   3.66
  </rating>
  <reviews>
   167720
  </reviews>
  <new>
   -
  </new>
  <exclusive>
   yes
  </exclusive>
 </clothing>
 <clothing>
  <id>
   268856284
  </id>
  <name>
   DC Hat C-6605
  </name>
  <category>
   Hat
  </category>
  <size>
   XXL
  </size>
  <color>
   Голубой
  </color>
  <material>
   Шерсть
  </material>
  <price>
   850908
  </price>
  <rating>
   3.59
  </rating>
  <reviews>
   544932
  </reviews>
  <new>
   -
  </new>
  <exclusive>
   yes
  </exclusive>
  <sporty>
   no
  </sporty>
 </clothing>
 <clothing>
  <id>
   363858343
  </id>
  <name>
   Reebok Hat B-2359
  </name>
  <category>
   Hat
  </category>
  <size>
   XXL
  </size>
  <color>
   Фиолетовый
  </color>
  <material>
   Хлопок
  </material>
  <price>
   278174
  </price>
  <rating>
   3.65
  </rating>
  <reviews>
   394632
  </reviews>
  <new>
   -
  </new>
  <exclusive>
   no
  </exclusive>
  <sporty>
   no
  </sporty>
 </clothing>
 <clothing>
  <id>
   893265460
  </id>
  <name>
   New Balance Hat L-4317
  </name>
  <category>
   Hat
  </category>
  <size>
   XL
  </size>
  <color>
   Фиолетовый
  </color>
  <material>
   Нейлон
  </material>
  <price>
   316067
  </price>
  <rating>
   4.06
  </rating>
  <reviews>
   134267
  </reviews>
  <new>
   +
  </new>
 </clothing>
 <clothing>
  <id>
   337314577
  </id>
  <name>
   Puma Jeans Q-3563
  </name>
  <category>
   Jeans
  </category>
  <size>
   XL
  </size>
  <color>
   Желтый
  </color>
  <material>
   Шелк
  </material>
  <price>
   468289
  </price>
  <rating>
   1.57
  </rating>
  <reviews>
   553314
  </reviews>
  <exclusive>
   no
  </exclusive>
 </clothing>
 <clothing>
  <id>
   693030815
  </id>
  <name>
   Reebok Skirt K-9880
  </name>
  <category>
   Skirt
  </category>
  <size>
   L
  </size>
  <color>
   Зеленый
  </color>
  <material>
   Шерсть
  </material>
  <price>
   668793
  </price>
  <rating>
   3.32
  </rating>
  <reviews>
   281501
  </reviews>
  <new>
   -
  </new>
  <exclusive>
   no
  </exclusive>
  <sporty>
   no
  </sporty>
 </clothing>
 <clothing>
  <id>
   543327968
  </id>
  <name>
   Asics Skirt H-1337
  </name>
  <category>
   Skirt
  </category>
  <size>
   XL
  </size>
  <color>
   Фиолетовый
  </color>
  <material>
   Вискоза
  </material>
  <price>
   307112
  </price>
  <rating>
   1.84
  </rating>
  <reviews>
   273352
  </reviews>
  <sporty>
   yes
  </sporty>
 </clothing>
 <clothing>
  <id>
   305012917
  </id>
  <name>
   Nike Jacket I-7339
  </name>
  <category>
   Jacket
  </category>
  <size>
   XXL
  </size>
  <color>
   Желтый
  </color>
  <material>
   Кожа
  </material>
  <price>
   351635
  </price>
  <rating>
   2.72
  </rating>
  <reviews>
   116929
  </reviews>
  <exclusive>
   yes
  </exclusive>
  <sporty>
   no
  </sporty>
 </clothing>
 <clothing>
  <id>
   566228680
  </id>
  <name>
   Reebok Handbags Y-7648
  </name>
  <category>
   Handbags
  </category>
  <size>
   L
  </size>
  <color>
   Голубой
  </color>
  <material>
   Хлопок
  </material>
  <price>
   737542
  </price>
  <rating>
   3.07
  </rating>
  <reviews>
   142129
  </reviews>
  <exclusive>
   no
  </exclusive>
  <sporty>
   yes
  </sporty>
 </clothing>
 <clothing>
  <id>
   939974674
  </id>
  <name>
   New Balance T-shirt F-7087
  </name>
  <category>
   T-shirt
  </category>
  <size>
   L
  </size>
  <color>
   Синий
  </color>
  <material>
   Лен
  </material>
  <price>
   221615
  </price>
  <rating>
   4.73
  </rating>
  <reviews>
   393326
  </reviews>
  <exclusive>
   no
  </exclusive>
  <sporty>
   yes
  </sporty>
 </clothing>
 <clothing>
  <id>
   760624184
  </id>
  <name>
   Brooks Jeans V-2126
  </name>
  <category>
   Jeans
  </category>
  <size>
   M
  </size>
  <color>
   Красный
  </color>
  <material>
   Вискоза
  </material>
  <price>
   379016
  </price>
  <rating>
   4.52
  </rating>
  <reviews>
   296611
  </reviews>
  <exclusive>
   no
  </exclusive>
  <sporty>
   no
  </sporty>
 </clothing>
 <clothing>
  <id>
   474189034
  </id>
  <name>
   Fila Jeans M-7767
  </name>
  <category>
   Jeans
  </category>
  <size>
   S
  </size>
  <color>
   Фиолетовый
  </color>
  <material>
   Лен
  </material>
  <price>
   266382
  </price>
  <rating>
   4.06
  </rating>
  <reviews>
   335368
  </reviews>
  <new>
   -
  </new>
  <sporty>
   yes
  </sporty>
 </clothing>
 <clothing>
  <id>
   475763025
  </id>
  <name>
   Reebok Gloves B-1534
  </name>
  <category>
   Gloves
  </category>
  <size>
   M
  </size>
  <color>
   Синий
  </color>
  <material>
   Кожа
  </material>
  <price>
   805424
  </price>
  <rating>
   3.23
  </rating>
  <reviews>
   746481
  </reviews>
  <new>
   -
  </new>
  <sporty>
   no
  </sporty>
 </clothing>
 <clothing>
  <id>
   285800845
  </id>
  <name>
   PleinSport Jacket F-4643
  </name>
  <category>
   Jacket
  </category>
  <size>
   L
  </size>
  <color>
   Красный
  </color>
  <material>
   Вискоза
  </material>
  <price>
   230051
  </price>
  <rating>
   3.24
  </rating>
  <reviews>
   425717
  </reviews>
  <new>
   +
  </new>
  <exclusive>
   no
  </exclusive>
  <sporty>
   yes
  </sporty>
 </clothing>
 <clothing>
  <id>
   134896604
  </id>
  <name>
   DC Pants B-7087
  </name>
  <category>
   Pants
  </category>
  <size>
   M
  </size>
  <color>
   Фиолетовый
  </color>
  <material>
   Лен
  </material>
  <price>
   694840
  </price>
  <rating>
   1.65
  </rating>
  <reviews>
   831975
  </reviews>
  <exclusive>
   no
  </exclusive>
  <sporty>
   no
  </sporty>
 </clothing>
 <clothing>
  <id>
   886524820
  </id>
  <name>
   Reebok Dress N-2161
  </name>
  <category>
   Dress
  </category>
  <size>
   S
  </size>
  <color>
   Зеленый
  </color>
  <material>
   Нейлон
  </material>
  <price>
   757807
  </price>
  <rating>
   1.57
  </rating>
  <reviews>
   371554
  </reviews>
  <new>
   +
  </new>
  <exclusive>
   yes
  </exclusive>
 </clothing>
 <clothing>
  <id>
   384245733
  </id>
  <name>
   Lacoste Dress T-2290
  </name>
  <category>
   Dress
  </category>
  <size>
   XL
  </size>
  <color>
   Оранжевый
  </color>
  <material>
   Вискоза
  </material>
  <price>
   113249
  </price>
  <rating>
   2.52
  </rating>
  <reviews>
   413533
  </reviews>
  <new>
   +
  </new>
  <sporty>
   yes
  </sporty>
 </clothing>
</clothing-items>
